quadricslam/__init__.py
quadricslam/quadricslam.py
quadricslam/quadricslam_states.py
quadricslam/utils.py
quadricslam/visualisation.py
quadricslam/data_associator/__init__.py
quadricslam/data_associator/quadric_iou_associator.py
quadricslam/data_source/__init__.py
quadricslam/data_source/realsense.py
quadricslam/data_source/tum_rgbd.py
quadricslam/detector/__init__.py
quadricslam/detector/faster_rcnn.py
quadricslam/visual_odometry/__init__.py
quadricslam/visual_odometry/rgbd_cv2.py
quadricslam_examples/__main__.py
quadricslam_examples/hello_manual_quadricslam.py
quadricslam_examples/hello_quadricslam.py
quadricslam_examples/realsense_python.py
quadricslam_examples/realsense_ros.py
quadricslam_examples/tum_rgbd.py
quadricslam-1.0.2.dist-info/LICENSE.txt
quadricslam-1.0.2.dist-info/METADATA
quadricslam-1.0.2.dist-info/WHEEL
quadricslam-1.0.2.dist-info/top_level.txt
quadricslam-1.0.2.dist-info/RECORD
