Metadata-Version: 2.1
Name: quadricslam
Version: 1.0.2
Summary: QuadricSLAM: SLAM systems with quadric landmarks
Author-email: Lachlan Nicholson <lachlan.nicholson@hdr.qut.edu.au>
Maintainer-email: Ben Talbot <b.talbot@qut.edu.au>
License: Copyright (c) 2020, Queensland University of Technology
Project-URL: Homepage, https://github.com/qcr/quadricslam
Project-URL: Issues, https://github.com/qcr/quadricslam/issues
Classifier: Development Status :: 4 - Beta
Classifier: License :: OSI Approved :: BSD License
Classifier: Operating System :: OS Independent
Classifier: Programming Language :: Python :: 3
License-File: LICENSE.txt
Requires-Dist: gtsam-quadrics
Requires-Dist: numpy
Requires-Dist: opencv-python
Requires-Dist: matplotlib
Requires-Dist: spatialmath-python
Requires-Dist: scipy
Requires-Dist: distinctipy
